{"Title":"South Park","Year":"1997\u2013","Rated":"TV-MA","Released":"13 Aug 1997","Runtime":"22 min","Genre":"Animation, Comedy","Writer":"Trey Parker, Matt Stone, Brian Graden","Actors":"Trey Parker, Matt Stone, Isaac Hayes","Plot":"Follows the misadventures of four irreverent grade-schoolers in the quiet, dysfunctional town of South Park, Colorado.","Language":"English","Country":"United States","Awards":"Won 5 Primetime Emmys. 20 wins \u0026 93 nominations total","Poster":"https://m.media-amazon.com/images/M/MV5BNTBlMzA3ZTUtODZjNi00NTM0LWExMjMtNjJhYzA3YTkwMWYwXkEyXkFqcGc@._V1_SX300.jpg","Ratings":[{"Source":"Internet Movie Database","Value":"8.7/10"}],"imdbRating":"8.7","imdbVotes":"422,709","imdbID":"tt0121955","Type":"series","DVD":"11 Mar 2008","Response":"True"}